lammps_data_parser/__init__.py
lammps_data_parser/lammps_data.py
lammps_data_parser-0.1.0.dist-info/licenses/LICENCE
lammps_data_parser-0.1.0.dist-info/METADATA
lammps_data_parser-0.1.0.dist-info/WHEEL
lammps_data_parser-0.1.0.dist-info/top_level.txt
lammps_data_parser-0.1.0.dist-info/RECORD
