Metadata-Version: 2.4
Name: lammps-data-parser
Version: 0.1.0
Summary: Python library for parsing and editing LAMMPS .data files
Author: Danis Bekmansurov
Author-email: riodan44a@gmail.com
Project-URL: Source, https://github.com/silentdan44/lammps-data-parser
Keywords: lammps molecular-dynamics parser
Classifier: Programming Language :: Python :: 3
Classifier: License :: OSI Approved :: MIT License
Classifier: Operating System :: OS Independent
Classifier: Intended Audience :: Science/Research
Classifier: Topic :: Scientific/Engineering :: Chemistry
Classifier: Topic :: Scientific/Engineering :: Physics
Requires-Python: >=3.6
License-File: LICENCE
Dynamic: author
Dynamic: author-email
Dynamic: classifier
Dynamic: keywords
Dynamic: license-file
Dynamic: project-url
Dynamic: requires-python
Dynamic: summary
